blessql/__init__.py
blessql/py.typed
blessql-0.1.3.dist-info/LICENSE.md
blessql-0.1.3.dist-info/WHEEL
blessql-0.1.3.dist-info/METADATA
blessql-0.1.3.dist-info/RECORD
